pyelectro/__init__.py
pyelectro/analysis.py
pyelectro/io.py
pyelectro/utils.py
pyelectro-0.2.7.dist-info/LICENSE
pyelectro-0.2.7.dist-info/METADATA
pyelectro-0.2.7.dist-info/WHEEL
pyelectro-0.2.7.dist-info/top_level.txt
pyelectro-0.2.7.dist-info/RECORD
