Metadata-Version: 2.1
Name: pyelectro
Version: 0.2.7
Summary: A Python library for analysis of electrophysiological data
Home-page: https://github.com/NeuralEnsemble/pyelectro
Author: Michael Vella, Padraig Gleeson
Author-email: mv333@cam.ac.uk, p.gleeson@gmail.com
License: BSD-2-clause
Classifier: License :: OSI Approved :: BSD License
Classifier: Development Status :: 3 - Alpha
Classifier: Intended Audience :: Science/Research
Classifier: Natural Language :: English
Classifier: Operating System :: OS Independent
Classifier: Programming Language :: Python :: 3.7
Classifier: Programming Language :: Python :: 3.8
Classifier: Programming Language :: Python :: 3.9
Classifier: Programming Language :: Python :: 3.10
Classifier: Programming Language :: Python :: 3.11
Classifier: Topic :: Scientific/Engineering
License-File: LICENSE
Requires-Dist: numpy
Requires-Dist: scipy
Requires-Dist: matplotlib
Provides-Extra: dev
Requires-Dist: pytest ; extra == 'dev'
Requires-Dist: pytest-cov ; extra == 'dev'
